xai_image_widget/__init__.py
xai_image_widget/_frontend.py
xai_image_widget/_version.py
xai_image_widget/image_widget.py
xai_image_widget/labextension/xai_image_widget-0.1.0.tgz
xai_image_widget/nbextension/__init__.py
xai_image_widget/nbextension/static/2b4bdbd58f6e1db62ed98e2cb7ce9ec2.js
xai_image_widget/nbextension/static/2e4232807d549beeaa137f9c37016a99.js
xai_image_widget/nbextension/static/359301716607328c22ff01b3fd86a3e1.js
xai_image_widget/nbextension/static/43418c08746f06440b4232c5a80f1763.js
xai_image_widget/nbextension/static/53ae571af3c116120a49c5c6e90f6515.js
xai_image_widget/nbextension/static/5766e224c010d5c5a2607ea479184221.js
xai_image_widget/nbextension/static/60d2ef21c45f95415325f99e5f452b3e.js
xai_image_widget/nbextension/static/72e2e7adac88b7d58740204dbd00491a.js
xai_image_widget/nbextension/static/7927e58753ab1f5ebd2c20c56fe4e584.js
xai_image_widget/nbextension/static/80e4b20f19b73d1cadf7485f99cd6cd9.js
xai_image_widget/nbextension/static/90c2a3b3927d109e55cbd84d9852f421.js
xai_image_widget/nbextension/static/a117f61a9666a0a130f6c40706a20156.js
xai_image_widget/nbextension/static/c2295aadaf4891497d7f6914935758ff.js
xai_image_widget/nbextension/static/c46625cbc7664f2d84278a1ade5f5d2c.js
xai_image_widget/nbextension/static/d0350ae4da4bc9e8328a3c5725f240f5.js
xai_image_widget/nbextension/static/e5966817487151f1eef7e4dcbdc94113.js
xai_image_widget/nbextension/static/eff920af50609d72e4c460aa0e783c38.js
xai_image_widget/nbextension/static/extension.js
xai_image_widget/nbextension/static/f0b19ba5a302c3fcb97294149cf2cb13.js
xai_image_widget/nbextension/static/index.js
xai_image_widget/nbextension/static/index.js.map
xai_image_widget/tests/__init__.py
xai_image_widget/tests/conftest.py
xai_image_widget/tests/test_image_widget.py
xai_image_widget/tests/test_nbextension_path.py
xai_image_widget-0.1.0.data/data/etc/jupyter/nbconfig/notebook.d/xai_image_widget.json
xai_image_widget-0.1.0.data/data/share/jupyter/lab/extensions/xai_image_widget-0.1.0.tgz
xai_image_widget-0.1.0.dist-info/METADATA
xai_image_widget-0.1.0.dist-info/WHEEL
xai_image_widget-0.1.0.dist-info/top_level.txt
xai_image_widget-0.1.0.dist-info/RECORD
